README.rst
setup.py
seotool/ZhengZhanSprider.py
seotool/__init__.py
seotool/content.py
seotool/rank_scroe.py
seotool/ranks.py
zhangte/__init__.py
zhangte/base.py
zhangte/jiqixuexi.py
zhangte/seo.py
zhangte/taobao.py
zhangte/ua.py
zhangte.egg-info/PKG-INFO
zhangte.egg-info/SOURCES.txt
zhangte.egg-info/dependency_links.txt
zhangte.egg-info/top_level.txt
zhangte.egg-info/zip-safe