Metadata-Version: 1.1
Name: zhangte
Version: 1.0.7
Summary: this is a test package for packing python liberaries tutorial.
Home-page: http://www.zhangte.org/
Author: 张特
Author-email: 353335447@qq.com
License: MIT
Keywords: test python package
Platform: UNKNOWN
Classifier: License :: OSI Approved :: MIT License
Classifier: Programming Language :: Python
Classifier: Intended Audience :: Developers
Classifier: Operating System :: OS Independent
